{
  "version": "0.7.6",
  "date": "2026-02-19",
  "description": "# Release Notes ## Chunkning: Alla dokument sökbara (OBJEKT-100) 38% av Lake-dokumenten (248/675) trunkerades vid 8000 tecken under embedding — allt efter var osynligt för sökning. Nu splittas långa dokument i semantiska chunks med source-type-medveten logik: - **Slack-loggar** splittas på meddelande-timestamps, trådsvar hålls med parent - **E-posttrådar** splittas på mailgränser (`On ... wrote:`, `*From:*`) - **Dokument** splittas på markdown-rubriker, paragrafer, med fixed-size fallback - **Kalender och transkript** oförändrade (redan hanterade) Varje chunkat dokument får en overview-chunk (part_0) med filnamn, sammanfattning och relationer, plus content-chunks (part_1..N). Befintlig transcript-chunkning och sökning via MCP fungerar som tidigare. **Resultat:** VectorDB gick från ~3600 till 7516 entries. All text som tidigare trunkerades är nu sökbar. ",
  "download_url": "https://github.com/joaekm/MyMemDist/releases/download/v0.7.6/MyMemory-Installer.dmg",
  "min_macos": "14.0"
}
